{
  "records": [
    {
      "id": "b3c38adc-9908-4dca-a08a-42cf76fe502a",
      "date": "29.10.2023",
      "status": "Inactive",
      "task": "Feed the cat",
      "tags": [
        "Animals",
        "Important",
        "Family"
      ],
      "start": [
        "30.10.2023, 15:06:07",
        "30.10.2023, 15:06:56",
        "30.10.2023, 15:09:53",
        "01.11.2023, 12:13:02"
      ],
      "end": [
        "30.10.2023, 15:06:37",
        "30.10.2023, 15:08:59",
        "30.10.2023, 15:09:57",
        "01.11.2023, 12:13:06"
      ]
    },
    {
      "id": "4b6c4fb9-743d-4b20-a1ed-5032fe3fb59d",
      "date": "29.10.2023",
      "status": "Inactive",
      "task": "Walk the dog",
      "tags": [
        "Animals",
        "Nature"
      ],
      "start": [
        "29.10.2023, 17:20:56",
        "29.10.2023, 18:04:56",
        "29.10.2023, 18:04:59",
        "29.10.2023, 18:05:11",
        "29.10.2023, 20:41:30",
        "30.10.2023, 15:06:16"
      ],
      "end": [
        "29.10.2023, 17:22:15",
        "29.10.2023, 18:04:57",
        "29.10.2023, 18:05:07",
        "29.10.2023, 18:05:21",
        "29.10.2023, 20:42:12",
        "30.10.2023, 15:06:21"
      ]
    },
    {
      "id": "42b48502-1615-4fdc-a6a7-02e098c09a0d",
      "date": "29.10.2023",
      "status": "Inactive",
      "task": "Go to the gym",
      "tags": [
        "Sport",
        "Hobby"
      ],
      "start": [
        "29.10.2023, 17:20:57",
        "29.10.2023, 17:43:44",
        "29.10.2023, 18:01:30",
        "30.10.2023, 15:06:17",
        "30.10.2023, 15:06:46",
        "30.10.2023, 15:06:48",
        "30.10.2023, 15:06:53"
      ],
      "end": [
        "29.10.2023, 17:22:19",
        "29.10.2023, 17:43:50",
        "29.10.2023, 18:01:35",
        "30.10.2023, 15:06:22",
        "30.10.2023, 15:06:47",
        "30.10.2023, 15:06:51",
        "30.10.2023, 15:06:59"
      ]
    }
  ],
  "settings": {
    "theme": "dark",
    "mode": "multiple"
  }
}